nirviz/__init__.py
nirviz/__main__.py
nirviz/nirviz.py
nirviz/style.yml
nirviz-0.1.4.dist-info/licenses/LICENSE
nirviz-0.1.4.dist-info/METADATA
nirviz-0.1.4.dist-info/WHEEL
nirviz-0.1.4.dist-info/top_level.txt
nirviz-0.1.4.dist-info/RECORD
