Metadata-Version: 2.4
Name: nirviz
Version: 0.1.4
Summary: Visualisation tool for the Neuromorphic Intermediate Representation
Author-email: Jens Egholm Pedersen <jens@jepedersen.dk>, Michail Rontionov <mrontionov@mront.io>
License-Expression: BSD-3-Clause
Project-URL: homepage, https://github.com/open-neuromorphic/nirviz
Classifier: Development Status :: 1 - Planning
Classifier: Intended Audience :: Developers
Classifier: Intended Audience :: Science/Research
Classifier: Programming Language :: Python :: 3
Classifier: Topic :: Scientific/Engineering :: Artificial Intelligence
Classifier: Topic :: Scientific/Engineering :: Information Analysis
Classifier: Topic :: Scientific/Engineering :: Mathematics
Classifier: Topic :: Scientific/Engineering :: Physics
Classifier: Topic :: Software Development :: Libraries :: Python Modules
Requires-Python: >=3.9
License-File: LICENSE
Requires-Dist: nir
Requires-Dist: graphviz
Requires-Dist: cairosvg
Requires-Dist: pyyaml
Dynamic: license-file
